decision_title/__init__.py
decision_title/__main__.py
decision_title-0.0.2.dist-info/WHEEL
decision_title-0.0.2.dist-info/METADATA
decision_title-0.0.2.dist-info/RECORD
